{
  "$themes": [
    {
      "name": "Global",
      "group": "Always enabled",
      "selectedTokenSets": {
        "foundations/fixed": "enabled",
        "foundations/scales": "enabled",
        "foundations/modular-scale": "enabled",
        "foundations/linear-scale": "enabled",
        "primitives/amber": "enabled",
        "primitives/base": "enabled",
        "primitives/black-alpha": "enabled",
        "primitives/blue": "enabled",
        "primitives/brand": "enabled",
        "primitives/bronze": "enabled",
        "primitives/brown": "enabled",
        "primitives/crimson": "enabled",
        "primitives/cyan": "enabled",
        "primitives/gold": "enabled",
        "primitives/grass": "enabled",
        "primitives/gray": "enabled",
        "primitives/green": "enabled",
        "primitives/indigo": "enabled",
        "primitives/iris": "enabled",
        "primitives/jade": "enabled",
        "primitives/lime": "enabled",
        "primitives/mauve": "enabled",
        "primitives/mint": "enabled",
        "primitives/olive": "enabled",
        "primitives/orange": "enabled",
        "primitives/pink": "enabled",
        "primitives/plum": "enabled",
        "primitives/purple": "enabled",
        "primitives/red": "enabled",
        "primitives/ruby": "enabled",
        "primitives/sage": "enabled",
        "primitives/sand": "enabled",
        "primitives/sky": "enabled",
        "primitives/slate": "enabled",
        "primitives/teal": "enabled",
        "primitives/tomato": "enabled",
        "primitives/violet": "enabled",
        "primitives/white-alpha": "enabled",
        "primitives/yellow": "enabled",
        "semantic/status-error": "enabled",
        "semantic/status-info": "enabled",
        "semantic/status-success": "enabled",
        "semantic/status-warning": "enabled",
        "spacing": "enabled",
        "width": "enabled",
        "container": "enabled",
        "paragraph": "enabled",
        "icon": "enabled",
        "foundations/typography": "enabled",
        "typography/roles": "enabled",
        "typography/styles": "enabled"
      }
    },
    {
      "name": "Gray",
      "group": "Gray flavor",
      "selectedTokenSets": {
        "semantic/gray-gray": "enabled"
      }
    },
    {
      "name": "Mauve",
      "group": "Gray flavor",
      "selectedTokenSets": {
        "semantic/gray-mauve": "enabled"
      }
    },
    {
      "name": "Olive",
      "group": "Gray flavor",
      "selectedTokenSets": {
        "semantic/gray-olive": "enabled"
      }
    },
    {
      "name": "Sage",
      "group": "Gray flavor",
      "selectedTokenSets": {
        "semantic/gray-sage": "enabled"
      }
    },
    {
      "name": "Sand",
      "group": "Gray flavor",
      "selectedTokenSets": {
        "semantic/gray-sand": "enabled"
      }
    },
    {
      "name": "Slate",
      "group": "Gray flavor",
      "selectedTokenSets": {
        "semantic/gray-slate": "enabled"
      }
    },
    {
      "name": "Amber",
      "group": "Accent color",
      "selectedTokenSets": {
        "semantic/accent-amber": "enabled"
      }
    },
    {
      "name": "Base",
      "group": "Accent color",
      "selectedTokenSets": {
        "semantic/accent-base": "enabled"
      }
    },
    {
      "name": "Blue",
      "group": "Accent color",
      "selectedTokenSets": {
        "semantic/accent-blue": "enabled"
      }
    },
    {
      "name": "Brand",
      "group": "Accent color",
      "selectedTokenSets": {
        "semantic/accent-brand": "enabled"
      }
    },
    {
      "name": "Bronze",
      "group": "Accent color",
      "selectedTokenSets": {
        "semantic/accent-bronze": "enabled"
      }
    },
    {
      "name": "Brown",
      "group": "Accent color",
      "selectedTokenSets": {
        "semantic/accent-brown": "enabled"
      }
    },
    {
      "name": "Crimson",
      "group": "Accent color",
      "selectedTokenSets": {
        "semantic/accent-crimson": "enabled"
      }
    },
    {
      "name": "Cyan",
      "group": "Accent color",
      "selectedTokenSets": {
        "semantic/accent-cyan": "enabled"
      }
    },
    {
      "name": "Gold",
      "group": "Accent color",
      "selectedTokenSets": {
        "semantic/accent-gold": "enabled"
      }
    },
    {
      "name": "Grass",
      "group": "Accent color",
      "selectedTokenSets": {
        "semantic/accent-grass": "enabled"
      }
    },
    {
      "name": "Green",
      "group": "Accent color",
      "selectedTokenSets": {
        "semantic/accent-green": "enabled"
      }
    },
    {
      "name": "Indigo",
      "group": "Accent color",
      "selectedTokenSets": {
        "semantic/accent-indigo": "enabled"
      }
    },
    {
      "name": "Iris",
      "group": "Accent color",
      "selectedTokenSets": {
        "semantic/accent-iris": "enabled"
      }
    },
    {
      "name": "Jade",
      "group": "Accent color",
      "selectedTokenSets": {
        "semantic/accent-jade": "enabled"
      }
    },
    {
      "name": "Lime",
      "group": "Accent color",
      "selectedTokenSets": {
        "semantic/accent-lime": "enabled"
      }
    },
    {
      "name": "Mint",
      "group": "Accent color",
      "selectedTokenSets": {
        "semantic/accent-mint": "enabled"
      }
    },
    {
      "name": "Orange",
      "group": "Accent color",
      "selectedTokenSets": {
        "semantic/accent-orange": "enabled"
      }
    },
    {
      "name": "Pink",
      "group": "Accent color",
      "selectedTokenSets": {
        "semantic/accent-pink": "enabled"
      }
    },
    {
      "name": "Plum",
      "group": "Accent color",
      "selectedTokenSets": {
        "semantic/accent-plum": "enabled"
      }
    },
    {
      "name": "Purple",
      "group": "Accent color",
      "selectedTokenSets": {
        "semantic/accent-purple": "enabled"
      }
    },
    {
      "name": "Red",
      "group": "Accent color",
      "selectedTokenSets": {
        "semantic/accent-red": "enabled"
      }
    },
    {
      "name": "Ruby",
      "group": "Accent color",
      "selectedTokenSets": {
        "semantic/accent-ruby": "enabled"
      }
    },
    {
      "name": "Sky",
      "group": "Accent color",
      "selectedTokenSets": {
        "semantic/accent-sky": "enabled"
      }
    },
    {
      "name": "Teal",
      "group": "Accent color",
      "selectedTokenSets": {
        "semantic/accent-teal": "enabled"
      }
    },
    {
      "name": "Tomato",
      "group": "Accent color",
      "selectedTokenSets": {
        "semantic/accent-tomato": "enabled"
      }
    },
    {
      "name": "Violet",
      "group": "Accent color",
      "selectedTokenSets": {
        "semantic/accent-violet": "enabled"
      }
    },
    {
      "name": "Yellow",
      "group": "Accent color",
      "selectedTokenSets": {
        "semantic/accent-yellow": "enabled"
      }
    },
    {
      "name": "Light",
      "group": "Color mode",
      "selectedTokenSets": {
        "appearance/light": "enabled"
      }
    },
    {
      "name": "Dark",
      "group": "Color mode",
      "selectedTokenSets": {
        "appearance/dark": "enabled"
      }
    },
    {
      "name": "Compact",
      "group": "Density",
      "selectedTokenSets": {
        "density/compact": "enabled"
      }
    },
    {
      "name": "Comfortable",
      "group": "Density",
      "selectedTokenSets": {
        "density/comfortable": "enabled"
      }
    },
    {
      "name": "Spacious",
      "group": "Density",
      "selectedTokenSets": {
        "density/spacious": "enabled"
      }
    },
    {
      "name": "Inter",
      "group": "Typeface",
      "selectedTokenSets": {
        "semantic/typeface-inter": "enabled"
      }
    },
    {
      "name": "Geist",
      "group": "Typeface",
      "selectedTokenSets": {
        "semantic/typeface-geist": "enabled"
      }
    },
    {
      "name": "Roboto",
      "group": "Typeface",
      "selectedTokenSets": {
        "semantic/typeface-roboto": "enabled"
      }
    },
    {
      "name": "System",
      "group": "Typeface",
      "selectedTokenSets": {
        "semantic/typeface-system": "enabled"
      }
    }
  ],
  "$metadata": {},
  "appearance/light": {
    "text": {
      "white": {
        "$value": "#ffffff",
        "$type": "color"
      },
      "brand-primary": {
        "$value": "{accent.11}",
        "$type": "color"
      },
      "brand-secondary": {
        "$value": "{accent.9}",
        "$type": "color"
      },
      "on-accent": {
        "$value": "{accent-contrast}",
        "$type": "color"
      },
      "error": {
        "$value": "{status-error.11}",
        "$type": "color"
      },
      "warning": {
        "$value": "{status-warning.11}",
        "$type": "color"
      },
      "success": {
        "$value": "{status-success.11}",
        "$type": "color"
      },
      "info": {
        "$value": "{status-info.11}",
        "$type": "color"
      },
      "neutral-primary": {
        "$value": "{neutral.12}",
        "$type": "color"
      },
      "neutral-secondary": {
        "$value": "{neutral.11}",
        "$type": "color"
      },
      "neutral-tertiary": {
        "$value": "{neutral.9}",
        "$type": "color"
      },
      "neutral-placeholder": {
        "$value": "{neutral.9}",
        "$type": "color"
      },
      "neutral-placeholder_subtle": {
        "$value": "{neutral.8}",
        "$type": "color"
      },
      "neutral-disabled": {
        "$value": "{neutral.8}",
        "$type": "color"
      }
    },
    "fg": {
      "white": {
        "$value": "#ffffff",
        "$type": "color"
      },
      "brand-primary": {
        "$value": "{accent.11}",
        "$type": "color"
      },
      "brand-secondary": {
        "$value": "{accent.9}",
        "$type": "color"
      },
      "on-accent": {
        "$value": "{accent-contrast}",
        "$type": "color"
      },
      "error-primary": {
        "$value": "{status-error.11}",
        "$type": "color"
      },
      "error-secondary": {
        "$value": "{status-error.9}",
        "$type": "color"
      },
      "warning-primary": {
        "$value": "{status-warning.11}",
        "$type": "color"
      },
      "warning-secondary": {
        "$value": "{status-warning.9}",
        "$type": "color"
      },
      "success-primary": {
        "$value": "{status-success.11}",
        "$type": "color"
      },
      "success-secondary": {
        "$value": "{status-success.9}",
        "$type": "color"
      },
      "info-primary": {
        "$value": "{status-info.11}",
        "$type": "color"
      },
      "info-secondary": {
        "$value": "{status-info.9}",
        "$type": "color"
      },
      "neutral-primary": {
        "$value": "{neutral.12}",
        "$type": "color"
      },
      "neutral-secondary": {
        "$value": "{neutral.11}",
        "$type": "color"
      },
      "neutral-tertiary": {
        "$value": "{neutral.9}",
        "$type": "color"
      },
      "neutral-quaternary": {
        "$value": "{neutral.8}",
        "$type": "color"
      },
      "neutral-disabled": {
        "$value": "{neutral.8}",
        "$type": "color"
      },
      "neutral-disabled_subtle": {
        "$value": "{neutral.7}",
        "$type": "color"
      }
    },
    "bg": {
      "overlay": {
        "$value": "{black-alpha.a9}",
        "$type": "color"
      },
      "surface": {
        "$value": "rgba(255, 255, 255, 0.936)",
        "$type": "color"
      },
      "panel": {
        "$value": "rgba(255, 255, 255, 0.65)",
        "$type": "color"
      },
      "brand-primary": {
        "$value": "{accent.3}",
        "$type": "color"
      },
      "brand-secondary": {
        "$value": "{accent.4}",
        "$type": "color"
      },
      "brand-solid": {
        "$value": "{accent.9}",
        "$type": "color"
      },
      "brand-solid_hover": {
        "$value": "{accent.10}",
        "$type": "color"
      },
      "error-primary": {
        "$value": "{status-error.3}",
        "$type": "color"
      },
      "error-secondary": {
        "$value": "{status-error.4}",
        "$type": "color"
      },
      "error-solid": {
        "$value": "{status-error.9}",
        "$type": "color"
      },
      "error-solid_hover": {
        "$value": "{status-error.10}",
        "$type": "color"
      },
      "warning-primary": {
        "$value": "{status-warning.3}",
        "$type": "color"
      },
      "warning-secondary": {
        "$value": "{status-warning.4}",
        "$type": "color"
      },
      "warning-solid": {
        "$value": "{status-warning.9}",
        "$type": "color"
      },
      "success-primary": {
        "$value": "{status-success.3}",
        "$type": "color"
      },
      "success-secondary": {
        "$value": "{status-success.4}",
        "$type": "color"
      },
      "success-solid": {
        "$value": "{status-success.9}",
        "$type": "color"
      },
      "info-primary": {
        "$value": "{status-info.3}",
        "$type": "color"
      },
      "info-secondary": {
        "$value": "{status-info.4}",
        "$type": "color"
      },
      "info-solid": {
        "$value": "{status-info.9}",
        "$type": "color"
      },
      "neutral-primary": {
        "$value": "{neutral.1}",
        "$type": "color"
      },
      "neutral-primary_hover": {
        "$value": "{neutral.2}",
        "$type": "color"
      },
      "neutral-primary-solid": {
        "$value": "{neutral.12}",
        "$type": "color"
      },
      "neutral-secondary": {
        "$value": "{neutral.2}",
        "$type": "color"
      },
      "neutral-secondary_hover": {
        "$value": "{neutral.3}",
        "$type": "color"
      },
      "neutral-secondary-solid": {
        "$value": "{neutral.11}",
        "$type": "color"
      },
      "neutral-tertiary": {
        "$value": "{neutral.3}",
        "$type": "color"
      },
      "neutral-quaternary": {
        "$value": "{neutral.4}",
        "$type": "color"
      },
      "neutral-active": {
        "$value": "{neutral.3}",
        "$type": "color"
      },
      "neutral-disabled": {
        "$value": "{neutral.3}",
        "$type": "color"
      },
      "neutral-disabled_subtle": {
        "$value": "{neutral.2}",
        "$type": "color"
      }
    },
    "border": {
      "brand": {
        "$value": "{accent.8}",
        "$type": "color"
      },
      "brand_subtle": {
        "$value": "{accent.6}",
        "$type": "color"
      },
      "focus-ring": {
        "$value": "{accent-alpha.a5}",
        "$type": "color"
      },
      "error": {
        "$value": "{status-error.8}",
        "$type": "color"
      },
      "error_subtle": {
        "$value": "{status-error.6}",
        "$type": "color"
      },
      "warning": {
        "$value": "{status-warning.8}",
        "$type": "color"
      },
      "success": {
        "$value": "{status-success.8}",
        "$type": "color"
      },
      "info": {
        "$value": "{status-info.8}",
        "$type": "color"
      },
      "neutral-primary": {
        "$value": "{neutral.6}",
        "$type": "color"
      },
      "neutral-secondary": {
        "$value": "{neutral.5}",
        "$type": "color"
      },
      "neutral-tertiary": {
        "$value": "{neutral.4}",
        "$type": "color"
      },
      "neutral-disabled": {
        "$value": "{neutral.5}",
        "$type": "color"
      },
      "neutral-disabled_subtle": {
        "$value": "{neutral.4}",
        "$type": "color"
      },
      "neutral-separator": {
        "$value": "{neutral.6}",
        "$type": "color"
      }
    },
    "surface": {
      "default": {
        "$value": "#ffffff",
        "$type": "color"
      },
      "raised": {
        "$value": "{neutral.2}",
        "$type": "color"
      },
      "sunken": {
        "$value": "{neutral.1}",
        "$type": "color"
      },
      "overlay": {
        "$value": "rgba(255, 255, 255, 0.936)",
        "$type": "color"
      }
    },
    "effect": {
      "shadow-color": {
        "$value": "rgba(24, 24, 26, 0.05)",
        "$type": "color"
      },
      "inner-shadow-color": {
        "$value": "rgba(252, 252, 253, 0.03)",
        "$type": "color"
      }
    }
  },
  "appearance/dark": {
    "text": {
      "white": {
        "$value": "#ffffff",
        "$type": "color"
      },
      "brand-primary": {
        "$value": "{accent-dark.11}",
        "$type": "color"
      },
      "brand-secondary": {
        "$value": "{accent-dark.9}",
        "$type": "color"
      },
      "on-accent": {
        "$value": "{accent-contrast}",
        "$type": "color"
      },
      "error": {
        "$value": "{status-error-dark.11}",
        "$type": "color"
      },
      "warning": {
        "$value": "{status-warning-dark.11}",
        "$type": "color"
      },
      "success": {
        "$value": "{status-success-dark.11}",
        "$type": "color"
      },
      "info": {
        "$value": "{status-info-dark.11}",
        "$type": "color"
      },
      "neutral-primary": {
        "$value": "{neutral-dark.12}",
        "$type": "color"
      },
      "neutral-secondary": {
        "$value": "{neutral-dark.11}",
        "$type": "color"
      },
      "neutral-tertiary": {
        "$value": "{neutral-dark.9}",
        "$type": "color"
      },
      "neutral-placeholder": {
        "$value": "{neutral-dark.9}",
        "$type": "color"
      },
      "neutral-placeholder_subtle": {
        "$value": "{neutral-dark.8}",
        "$type": "color"
      },
      "neutral-disabled": {
        "$value": "{neutral-dark.8}",
        "$type": "color"
      }
    },
    "fg": {
      "white": {
        "$value": "#ffffff",
        "$type": "color"
      },
      "brand-primary": {
        "$value": "{accent-dark.11}",
        "$type": "color"
      },
      "brand-secondary": {
        "$value": "{accent-dark.9}",
        "$type": "color"
      },
      "on-accent": {
        "$value": "{accent-contrast}",
        "$type": "color"
      },
      "error-primary": {
        "$value": "{status-error-dark.11}",
        "$type": "color"
      },
      "error-secondary": {
        "$value": "{status-error-dark.9}",
        "$type": "color"
      },
      "warning-primary": {
        "$value": "{status-warning-dark.11}",
        "$type": "color"
      },
      "warning-secondary": {
        "$value": "{status-warning-dark.9}",
        "$type": "color"
      },
      "success-primary": {
        "$value": "{status-success-dark.11}",
        "$type": "color"
      },
      "success-secondary": {
        "$value": "{status-success-dark.9}",
        "$type": "color"
      },
      "info-primary": {
        "$value": "{status-info-dark.11}",
        "$type": "color"
      },
      "info-secondary": {
        "$value": "{status-info-dark.9}",
        "$type": "color"
      },
      "neutral-primary": {
        "$value": "{neutral-dark.12}",
        "$type": "color"
      },
      "neutral-secondary": {
        "$value": "{neutral-dark.11}",
        "$type": "color"
      },
      "neutral-tertiary": {
        "$value": "{neutral-dark.9}",
        "$type": "color"
      },
      "neutral-quaternary": {
        "$value": "{neutral-dark.8}",
        "$type": "color"
      },
      "neutral-disabled": {
        "$value": "{neutral-dark.8}",
        "$type": "color"
      },
      "neutral-disabled_subtle": {
        "$value": "{neutral-dark.7}",
        "$type": "color"
      }
    },
    "bg": {
      "overlay": {
        "$value": "{black-alpha.a9}",
        "$type": "color"
      },
      "surface": {
        "$value": "rgba(0, 0, 0, 0.891)",
        "$type": "color"
      },
      "panel": {
        "$value": "{neutral-dark.1}",
        "$type": "color"
      },
      "brand-primary": {
        "$value": "{accent-dark.3}",
        "$type": "color"
      },
      "brand-secondary": {
        "$value": "{accent-dark.4}",
        "$type": "color"
      },
      "brand-solid": {
        "$value": "{accent-dark.9}",
        "$type": "color"
      },
      "brand-solid_hover": {
        "$value": "{accent-dark.10}",
        "$type": "color"
      },
      "error-primary": {
        "$value": "{status-error-dark.3}",
        "$type": "color"
      },
      "error-secondary": {
        "$value": "{status-error-dark.4}",
        "$type": "color"
      },
      "error-solid": {
        "$value": "{status-error-dark.9}",
        "$type": "color"
      },
      "error-solid_hover": {
        "$value": "{status-error-dark.10}",
        "$type": "color"
      },
      "warning-primary": {
        "$value": "{status-warning-dark.3}",
        "$type": "color"
      },
      "warning-secondary": {
        "$value": "{status-warning-dark.4}",
        "$type": "color"
      },
      "warning-solid": {
        "$value": "{status-warning-dark.9}",
        "$type": "color"
      },
      "success-primary": {
        "$value": "{status-success-dark.3}",
        "$type": "color"
      },
      "success-secondary": {
        "$value": "{status-success-dark.4}",
        "$type": "color"
      },
      "success-solid": {
        "$value": "{status-success-dark.9}",
        "$type": "color"
      },
      "info-primary": {
        "$value": "{status-info-dark.3}",
        "$type": "color"
      },
      "info-secondary": {
        "$value": "{status-info-dark.4}",
        "$type": "color"
      },
      "info-solid": {
        "$value": "{status-info-dark.9}",
        "$type": "color"
      },
      "neutral-primary": {
        "$value": "{neutral-dark.1}",
        "$type": "color"
      },
      "neutral-primary_hover": {
        "$value": "{neutral-dark.2}",
        "$type": "color"
      },
      "neutral-primary-solid": {
        "$value": "{neutral-dark.12}",
        "$type": "color"
      },
      "neutral-secondary": {
        "$value": "{neutral-dark.2}",
        "$type": "color"
      },
      "neutral-secondary_hover": {
        "$value": "{neutral-dark.3}",
        "$type": "color"
      },
      "neutral-secondary-solid": {
        "$value": "{neutral-dark.11}",
        "$type": "color"
      },
      "neutral-tertiary": {
        "$value": "{neutral-dark.3}",
        "$type": "color"
      },
      "neutral-quaternary": {
        "$value": "{neutral-dark.4}",
        "$type": "color"
      },
      "neutral-active": {
        "$value": "{neutral-dark.3}",
        "$type": "color"
      },
      "neutral-disabled": {
        "$value": "{neutral-dark.3}",
        "$type": "color"
      },
      "neutral-disabled_subtle": {
        "$value": "{neutral-dark.2}",
        "$type": "color"
      }
    },
    "border": {
      "brand": {
        "$value": "{accent-dark.8}",
        "$type": "color"
      },
      "brand_subtle": {
        "$value": "{accent-dark.6}",
        "$type": "color"
      },
      "focus-ring": {
        "$value": "{accent-dark-alpha.a5}",
        "$type": "color"
      },
      "error": {
        "$value": "{status-error-dark.8}",
        "$type": "color"
      },
      "error_subtle": {
        "$value": "{status-error-dark.6}",
        "$type": "color"
      },
      "warning": {
        "$value": "{status-warning-dark.8}",
        "$type": "color"
      },
      "success": {
        "$value": "{status-success-dark.8}",
        "$type": "color"
      },
      "info": {
        "$value": "{status-info-dark.8}",
        "$type": "color"
      },
      "neutral-primary": {
        "$value": "{neutral-dark.6}",
        "$type": "color"
      },
      "neutral-secondary": {
        "$value": "{neutral-dark.5}",
        "$type": "color"
      },
      "neutral-tertiary": {
        "$value": "{neutral-dark.4}",
        "$type": "color"
      },
      "neutral-disabled": {
        "$value": "{neutral-dark.5}",
        "$type": "color"
      },
      "neutral-disabled_subtle": {
        "$value": "{neutral-dark.4}",
        "$type": "color"
      },
      "neutral-separator": {
        "$value": "{neutral-dark.6}",
        "$type": "color"
      }
    },
    "surface": {
      "default": {
        "$value": "{neutral-dark.1}",
        "$type": "color"
      },
      "raised": {
        "$value": "{neutral-dark.2}",
        "$type": "color"
      },
      "sunken": {
        "$value": "{neutral-dark.1}",
        "$type": "color"
      },
      "overlay": {
        "$value": "rgba(0, 0, 0, 0.891)",
        "$type": "color"
      }
    },
    "effect": {
      "shadow-color": {
        "$value": "rgba(0, 0, 0, 0.25)",
        "$type": "color"
      },
      "inner-shadow-color": {
        "$value": "rgba(252, 252, 253, 0.02)",
        "$type": "color"
      }
    }
  }
}